django_asgi_lifespan/__init__.py
django_asgi_lifespan/asgi.py
django_asgi_lifespan/compat.py
django_asgi_lifespan/dispatcher.py
django_asgi_lifespan/errors.py
django_asgi_lifespan/events.py
django_asgi_lifespan/handler.py
django_asgi_lifespan/middleware.py
django_asgi_lifespan/py.typed
django_asgi_lifespan/register.py
django_asgi_lifespan/signals.py
django_asgi_lifespan/testing.py
django_asgi_lifespan/types.py
django_asgi_lifespan-0.5.1.dist-info/WHEEL
django_asgi_lifespan-0.5.1.dist-info/METADATA
django_asgi_lifespan-0.5.1.dist-info/RECORD
