Metadata-Version: 2.4
Name: django-asgi-lifespan
Version: 0.5.1
Summary: Django ASGI handler with Lifespan Protocol support.
Keywords: django,asgi,lifespan,async,signals
Author: Václav Dohnal
Author-email: Václav Dohnal <vaclav.dohnal@gmail.com>
License-Expression: MIT
Classifier: Development Status :: 4 - Beta
Classifier: Intended Audience :: Developers
Classifier: License :: OSI Approved :: MIT License
Classifier: Natural Language :: English
Classifier: Programming Language :: Python :: 3
Classifier: Programming Language :: Python :: 3.10
Classifier: Programming Language :: Python :: 3.11
Classifier: Programming Language :: Python :: 3.12
Classifier: Programming Language :: Python :: 3.13
Classifier: Programming Language :: Python :: 3.14
Classifier: Programming Language :: Python :: 3 :: Only
Classifier: Operating System :: OS Independent
Classifier: Environment :: Web Environment
Classifier: Framework :: AsyncIO
Classifier: Framework :: Django
Classifier: Framework :: Django :: 4.2
Classifier: Framework :: Django :: 5.0
Classifier: Framework :: Django :: 5.1
Classifier: Framework :: Django :: 5.2
Classifier: Framework :: Django :: 6.0
Requires-Dist: django>=4.2,!=5.0.0,!=5.0.1,!=5.0.2,<6.1
Requires-Dist: asgiref>=3.0.0
Requires-Python: >=3.10, <3.15
Project-URL: bug-tracker, https://github.com/illagrenan/django-asgi-lifespan/issues
Project-URL: changelog, https://illagrenan.github.io/django-asgi-lifespan/changelog/
Project-URL: documentation, https://illagrenan.github.io/django-asgi-lifespan/
Project-URL: homepage, https://github.com/illagrenan/django-asgi-lifespan
Project-URL: repository, https://github.com/illagrenan/django-asgi-lifespan
